mxu/__init__.py
mxu/clstools.py
mxu/itertools.py
mxu/maps.py
mxu/py.typed
mxu/sanity.py
mxu-0.0.6.dist-info/WHEEL
mxu-0.0.6.dist-info/METADATA
mxu-0.0.6.dist-info/RECORD
